{
    "title": "Info-2",
    "timeout": 15000,
    "steps": [
        {
            "type": "setViewport",
            "width": 910,
            "height": 754,
            "deviceScaleFactor": 1,
            "isMobile": false,
            "hasTouch": false,
            "isLandscape": false
        },
        {
            "type": "navigate",
            "url": "https://www.google.com/",
            "assertedEvents": [
                {
                    "type": "navigation",
                    "url": "https://www.google.com/",
                    "title": "Google"
                }
            ]
        },
        {
            "type": "navigate",
            "url": "https://www.epicurious.com/",
            "assertedEvents": [
                {
                    "type": "navigation",
                    "url": "https://www.epicurious.com/",
                    "title": ""
                }
            ]
        },
        {
            "type": "click",
            "target": "main",
            "selectors": [
                [
                    "aria/search"
                ],
                [
                    "div.StackedNavigationBottom-dpcakX [data-testid='TextFieldInput__q']"
                ],
                [
                    "xpath///*[@data-testid=\"TextFieldInput__q\"]"
                ],
                [
                    "pierce/div.StackedNavigationBottom-dpcakX [data-testid='TextFieldInput__q']"
                ]
            ],
            "offsetY": 17,
            "offsetX": 203
        },
        {
            "type": "change",
            "value": "vegan cake",
            "selectors": [
                [
                    "aria/search"
                ],
                [
                    "div.StackedNavigationBottom-dpcakX [data-testid='TextFieldInput__q']"
                ],
                [
                    "xpath///*[@data-testid=\"TextFieldInput__q\"]"
                ],
                [
                    "pierce/div.StackedNavigationBottom-dpcakX [data-testid='TextFieldInput__q']"
                ]
            ],
            "target": "main"
        },
        {
            "type": "keyDown",
            "target": "main",
            "key": "Enter",
            "assertedEvents": [
                {
                    "type": "navigation",
                    "url": "https://www.epicurious.com/search?q=vegan+cake",
                    "title": "Search | Epicurious"
                }
            ]
        },
        {
            "type": "keyUp",
            "key": "Enter",
            "target": "main"
        },
        {
            "type": "click",
            "target": "main",
            "selectors": [
                [
                    "[data-testid='RowWrapper'] > div > div > div > div.BaseWrap-sc-gjQpdd span.dropdown__icon"
                ],
                [
                    "xpath///*[@data-testid=\"dropdown-wrapper\"]/div/div/div[2]/span[2]"
                ],
                [
                    "pierce/[data-testid='RowWrapper'] > div > div > div > div.BaseWrap-sc-gjQpdd span.dropdown__icon"
                ]
            ],
            "offsetY": 22.5703125,
            "offsetX": 5
        },
        {
            "type": "click",
            "target": "main",
            "selectors": [
                [
                    "#react-select-sort-option-2"
                ],
                [
                    "xpath///*[@id=\"react-select-sort-option-2\"]"
                ],
                [
                    "pierce/#react-select-sort-option-2"
                ]
            ],
            "offsetY": 17.203125,
            "offsetX": 75
        },
        {
            "type": "click",
            "target": "main",
            "selectors": [
                [
                    "aria/Vegan Chocolate Chip Cookies[role=\"heading\"]"
                ],
                [
                    "div.search_result_item-65a93d1a8347d64f64ac165a h2"
                ],
                [
                    "xpath///*[@data-testid=\"ClampWrapper\"]/div/a/h2"
                ],
                [
                    "pierce/div.search_result_item-65a93d1a8347d64f64ac165a h2"
                ],
                [
                    "text/Vegan Chocolate Chip"
                ]
            ],
            "offsetY": 40.9609375,
            "offsetX": 52,
            "assertedEvents": [
                {
                    "type": "navigation",
                    "url": "https://www.epicurious.com/recipes/food/views/ba-syn-vegan-chocolate-chip-cookies",
                    "title": "Vegan Chocolate Chip Cookies Recipe | Epicurious"
                }
            ]
        }
    ]
}
